<!-- hauptScreenSetup -->
<screen name="hauptScreenSetup" position="center,center" size="1280,720" flags="wfNoBorder" backgroundColor="#80ffffff" >
    <widget backgroundColor="#20000000" font="mediaportal_clean;40" halign="right" position="960,6" render="Label" size="133,60" source="global.CurrentTime" transparent="1" valign="center">
        <convert type="ClockToText">Default</convert>
    </widget>
    <widget backgroundColor="#20000000" font="mediaportal_clean;20" position="1113,6" render="Label" size="153,60" source="global.CurrentTime" transparent="1" valign="center">
        <convert type="ClockToText">Format:%A                   %d. %B</convert>
    </widget>
  <eLabel backgroundColor="#20000000" text="MediaPortal" font="mediaportal_clean;33" halign="left" valign="center" position="33,6" shadowColor="#00000000" shadowOffset="2,2" size="800,60" transparent="1" />
  <eLabel name="bg_up" position="6,6" size="1266,60" zPosition="-1" backgroundColor="#20000000" />
  <eLabel name="bg_titel" position="6,73" size="840,73" zPosition="-1" backgroundColor="#20000000" />
  <eLabel name="bg_list" position="6,153" size="840,526" zPosition="-1" backgroundColor="#20000000" />
  <eLabel name="bg_cover" position="853,73" size="419,606" zPosition="0" backgroundColor="#20000000" />
  <eLabel name="bg_down" position="6,686" size="1266,26" zPosition="-1" backgroundColor="#20000000" />
  <eLabel name="button red" position="10,711" size="243,1" backgroundColor="#00f23d21" zPosition="1" />
  <eLabel name="button green" position="256,711" size="243,1" backgroundColor="#0031a500" zPosition="1" />
  <eLabel name="button yellow" position="503,711" size="243,1" backgroundColor="#00e5b243" zPosition="1" />
  <eLabel name="button blue" position="750,711" size="243,1" backgroundColor="#000064c7" zPosition="1" />
  <widget backgroundColor="#20000000" name="config" position="13,160" size="826,494" scrollbarMode="showOnDemand" transparent="1" itemHeight="26"  />
  <widget name="title" position="13,80" size="826,60" backgroundColor="#20000000" transparent="1" font="mediaportal_clean;33" valign="center" halign="center" />
  <widget name="F1" position="10,686" size="243,26" transparent="1" font="mediaportal; 16" backgroundColor="#20000000" valign="center" halign="center" zPosition="1" />
  <widget name="F2" position="256,686" size="243,26" transparent="1" font="mediaportal; 16" backgroundColor="#20000000" valign="center" halign="center" zPosition="1" />
  <widget name="F3" position="503,686" size="243,26" transparent="1" font="mediaportal; 16" backgroundColor="#20000000" valign="center" halign="center" zPosition="1" />
  <widget name="F4" position="750,686" size="243,26" transparent="1" font="mediaportal; 16" backgroundColor="#20000000" valign="center" halign="center" zPosition="1" />
  <eLabel name="button ok" position="1160,690" size="40,18" backgroundColor="#00000000" text="OK" font="mediaportal; 10" foregroundColor="#00ffffff" halign="center" valign="center" shadowColor="#00000000" shadowOffset="-3,-3" zPosition="1" />
  <eLabel name="button exit" position="1213,690" size="40,18" backgroundColor="#00000000" text="EXIT" font="mediaportal; 10" foregroundColor="#00ffffff" halign="center" valign="center" shadowColor="#00000000" shadowOffset="-3,-3" zPosition="1" />
  <eLabel name="button bouq" position="1107,690" size="40,18" backgroundColor="#00000000" text="BOUQ" font="mediaportal; 10" foregroundColor="#00ffffff" halign="center" valign="center" shadowColor="#00000000" shadowOffset="-3,-3" zPosition="1" />
  <eLabel name="button ok bg" position="1159,689" size="42,20" backgroundColor="#00616161" zPosition="0" />
  <eLabel name="button exit bg" position="1212,689" size="42,20" backgroundColor="#00616161" zPosition="0" />
  <eLabel name="button bouq bg" position="1106,689" size="42,20" backgroundColor="#00616161" zPosition="0" />
</screen>